alibabacloud_pailangstudio20240710/__init__.py
alibabacloud_pailangstudio20240710/client.py
alibabacloud_pailangstudio20240710/models/__init__.py
alibabacloud_pailangstudio20240710/models/_auto_update_config.py
alibabacloud_pailangstudio20240710/models/_connection.py
alibabacloud_pailangstudio20240710/models/_create_knowledge_base_job_request.py
alibabacloud_pailangstudio20240710/models/_create_knowledge_base_job_response.py
alibabacloud_pailangstudio20240710/models/_create_knowledge_base_job_response_body.py
alibabacloud_pailangstudio20240710/models/_create_knowledge_base_request.py
alibabacloud_pailangstudio20240710/models/_create_knowledge_base_response.py
alibabacloud_pailangstudio20240710/models/_create_knowledge_base_response_body.py
alibabacloud_pailangstudio20240710/models/_delete_knowledge_base_job_request.py
alibabacloud_pailangstudio20240710/models/_delete_knowledge_base_job_response.py
alibabacloud_pailangstudio20240710/models/_delete_knowledge_base_job_response_body.py
alibabacloud_pailangstudio20240710/models/_delete_knowledge_base_request.py
alibabacloud_pailangstudio20240710/models/_delete_knowledge_base_response.py
alibabacloud_pailangstudio20240710/models/_delete_knowledge_base_response_body.py
alibabacloud_pailangstudio20240710/models/_deployment.py
alibabacloud_pailangstudio20240710/models/_ecs_spec.py
alibabacloud_pailangstudio20240710/models/_flow.py
alibabacloud_pailangstudio20240710/models/_flow_run.py
alibabacloud_pailangstudio20240710/models/_flow_template.py
alibabacloud_pailangstudio20240710/models/_get_knowledge_base_job_request.py
alibabacloud_pailangstudio20240710/models/_get_knowledge_base_job_response.py
alibabacloud_pailangstudio20240710/models/_get_knowledge_base_job_response_body.py
alibabacloud_pailangstudio20240710/models/_get_knowledge_base_request.py
alibabacloud_pailangstudio20240710/models/_get_knowledge_base_response.py
alibabacloud_pailangstudio20240710/models/_get_knowledge_base_response_body.py
alibabacloud_pailangstudio20240710-1.0.0.dist-info/LICENSE
alibabacloud_pailangstudio20240710-1.0.0.dist-info/METADATA
alibabacloud_pailangstudio20240710-1.0.0.dist-info/WHEEL
alibabacloud_pailangstudio20240710-1.0.0.dist-info/top_level.txt
alibabacloud_pailangstudio20240710-1.0.0.dist-info/RECORD
